homonculi/__init__.py
homonculi/config.py
homonculi/file_utilities.py
homonculi/job.py
homonculi/openai_api.py
homonculi/simulate.py
homonculi/stats_utilities.py
homonculi/text_utilities.py
homonculi/quizzes/__init__.py
homonculi/quizzes/canvas_conversion.py
homonculi/quizzes/loader.py
homonculi/quizzes/questions.py
homonculi/quizzes/quiz_analysis.py
homonculi/quizzes/quizzes.py
homonculi/schemas/prompt_function.py
homonculi-0.1.7.dist-info/licenses/LICENSE
homonculi-0.1.7.dist-info/METADATA
homonculi-0.1.7.dist-info/WHEEL
homonculi-0.1.7.dist-info/entry_points.txt
homonculi-0.1.7.dist-info/top_level.txt
homonculi-0.1.7.dist-info/RECORD
