Metadata-Version: 2.4
Name: homonculi
Version: 0.1.7
Summary: A simulation tool for emulating students taking quizzes.
Author-email: Austin Cory Bart <acbart@udel.edu>
License: Copyright (c) 2025 Austin Cory bart
Requires-Python: >=3.9
License-File: LICENSE
Requires-Dist: markdown
Requires-Dist: canvasapi
Requires-Dist: python-docx
Requires-Dist: openai
Requires-Dist: tqdm~=4.66.2
Requires-Dist: pandas
Requires-Dist: matplotlib
Requires-Dist: pyyaml~=6.0.1
Requires-Dist: requests~=2.31.0
Requires-Dist: fpdf2
Requires-Dist: pytest
Requires-Dist: requests-cache
Requires-Dist: setuptools~=69.0.3
Requires-Dist: bakery
Requires-Dist: pedal
Requires-Dist: python-frontmatter
Dynamic: license-file
